{
  "gitSyncId": "65dd6c718a029270bf94d472_65dd74f0e3fc5c361ade573a",
  "id": "USERS_DeleteQuery",
  "pluginId": "snowflake-plugin",
  "pluginType": "DB",
  "unpublishedAction": {
    "actionConfiguration": {
      "body": "DELETE FROM PUBLIC.USERS\n  WHERE EMAIL = {{data_table.triggeredRow.EMAIL}};",
      "encodeParamsToggle": true,
      "paginationType": "NONE",
      "pluginSpecifiedTemplates": [
        {
          "value": true
        }
      ],
      "timeoutInMillisecond": 10000
    },
    "confirmBeforeExecute": false,
    "datasource": {
      "id": "snow",
      "isAutoGenerated": false,
      "name": "snow",
      "pluginId": "snowflake-plugin"
    },
    "executeOnLoad": false,
    "name": "DeleteQuery",
    "pageId": "USERS",
    "userSetOnLoad": false
  }
}